{"stat.craftItem.minecraft.chorus_fruit_popped":755,"stat.useItem.minecraft.bow":2676,"stat.useItem.minecraft.quartz_block":3,"stat.useItem.minecraft.painting":480,"stat.drop.minecraft.gunpowder":70,"stat.drop.minecraft.redstone":5,"stat.pickup.minecraft.dark_oak_boat":5,"stat.mineBlock.minecraft.stained_glass":2126,"stat.drop.minecraft.enchanted_book":1,"stat.mineBlock.minecraft.web":191,"stat.drop.minecraft.iron_sword":5,"stat.pickup.minecraft.rotten_flesh":1830,"stat.useItem.minecraft.diamond_hoe":4,"stat.craftItem.minecraft.stone_axe":28,"stat.useItem.minecraft.vine":9,"stat.pickup.minecraft.cobblestone_wall":16,"stat.pickup.minecraft.bucket":19,"stat.useItem.minecraft.rail":2690,"stat.killEntity.Enderman":18768,"stat.drop.minecraft.elytra":15,"stat.useItem.minecraft.anvil":17,"stat.craftItem.minecraft.iron_shovel":59,"stat.pickup.minecraft.brown_mushroom":35,"stat.breakItem.minecraft.bow":1,"stat.mineBlock.minecraft.end_stone":277,"stat.killEntity.Villager":2,"stat.useItem.minecraft.spider_eye":1,"stat.useItem.minecraft.iron_pickaxe":57759,"stat.pickup.minecraft.stained_hardened_clay":74,"stat.pickup.minecraft.double_plant":25,"stat.drop.minecraft.diamond_chestplate":2,"stat.mineBlock.minecraft.sticky_piston":17,"stat.furnaceInteraction":3670,"stat.useItem.minecraft.nether_wart":37,"stat.mineBlock.minecraft.chorus_plant":87,"stat.drop.minecraft.chorus_fruit":4,"stat.pickup.minecraft.nether_brick":388,"stat.craftItem.minecraft.leather_helmet":3,"stat.pickup.minecraft.sponge":773,"stat.useItem.minecraft.end_stone":137,"stat.mineBlock.minecraft.wooden_button":23,"stat.pickup.minecraft.hay_block":3,"stat.craftItem.minecraft.golden_leggings":1,"stat.useItem.minecraft.fence":483,"stat.craftItem.minecraft.daylight_detector":4,"stat.mineBlock.minecraft.sponge":1632,"stat.useItem.minecraft.cauldron":2,"stat.useItem.minecraft.flint_and_steel":763,"stat.mineBlock.minecraft.fence":757,"stat.mineBlock.minecraft.sea_lantern":492,"stat.useItem.minecraft.wheat_seeds":2534,"stat.killEntity.Husk":8,"stat.pickup.minecraft.emerald":30,"stat.craftItem.minecraft.dark_oak_boat":6,"stat.pickup.minecraft.lever":81,"stat.deaths":516,"stat.pickup.minecraft.bowl":3,"stat.craftItem.minecraft.melon_seeds":9,"stat.pickup.minecraft.egg":3665,"stat.craftItem.minecraft.item_frame":69,"stat.craftItem.minecraft.wooden_shovel":1,"stat.pickup.minecraft.clock":2,"stat.craftItem.minecraft.iron_pickaxe":178,"stat.pickup.minecraft.sea_lantern":56,"stat.pickup.minecraft.item_frame":3,"stat.craftItem.minecraft.repeater":211,"stat.craftItem.minecraft.cooked_mutton":43,"stat.fishCaught":285,"stat.pickup.minecraft.cooked_mutton":128,"stat.chestOpened":15549,"stat.useItem.minecraft.lapis_ore":5,"stat.craftItem.minecraft.mushroom_stew":2,"stat.craftItem.minecraft.sign":354,"stat.pickup.minecraft.iron_sword":114,"stat.killEntity.Vex":3,"stat.pickup.minecraft.lapis_ore":51,"stat.craftItem.minecraft.quartz_block":171,"stat.pickup.minecraft.gold_nugget":329,"stat.pickup.minecraft.chorus_flower":55,"stat.craftItem.minecraft.coal":1181,"stat.craftItem.minecraft.ender_chest":11,"stat.pickup.minecraft.carrot":1473,"stat.drop.minecraft.stone_sword":6,"stat.crouchOneCm":7668165,"stat.pickup.minecraft.rail":1246,"stat.craftItem.minecraft.iron_ingot":3984,"stat.pickup.minecraft.ender_chest":1,"stat.drop.minecraft.slime_ball":7,"stat.craftingTableInteraction":2364,"stat.pickup.minecraft.repeater":154,"stat.pickup.minecraft.wooden_pickaxe":7,"stat.mineBlock.minecraft.log2":15416,"stat.drop.minecraft.double_plant":1,"stat.useItem.minecraft.dark_oak_fence":2241,"stat.pickup.minecraft.dye":2650,"stat.pickup.minecraft.planks":1260,"stat.drop.minecraft.minecart":2,"stat.mineBlock.minecraft.blue_glazed_terracotta":27,"stat.useItem.minecraft.lime_glazed_terracotta":16,"stat.drop.minecraft.carpet":13,"stat.mineBlock.minecraft.ender_chest":6,"stat.mineBlock.minecraft.daylight_detector":7,"stat.flowerPotted":11,"stat.drop.minecraft.rotten_flesh":63,"stat.pickup.minecraft.magma":275,"stat.drop.minecraft.iron_door":3,"stat.useItem.minecraft.yellow_flower":3,"stat.drop.minecraft.sapling":411,"stat.pickup.minecraft.chicken":533,"stat.drop.minecraft.gold_nugget":4,"stat.pickup.minecraft.tipped_arrow":381,"stat.pickup.minecraft.end_stone":456,"stat.breakItem.minecraft.stone_shovel":48,"stat.craftItem.minecraft.bucket":188,"stat.useItem.minecraft.iron_sword":9455,"stat.craftItem.minecraft.planks":47443,"stat.useItem.minecraft.barrier":94,"stat.mineBlock.minecraft.prismarine":19296,"stat.craftItem.minecraft.fishing_rod":10,"stat.pickup.minecraft.stone_sword":42,"stat.useItem.minecraft.daylight_detector":9,"stat.pickup.minecraft.book":77,"stat.useItem.minecraft.stonebrick":3772,"stat.craftItem.minecraft.wooden_door":15,"stat.useItem.minecraft.green_glazed_terracotta":5,"stat.mineBlock.minecraft.waterlily":3,"stat.useItem.minecraft.monster_egg":1,"stat.pickup.minecraft.orange_glazed_terracotta":2,"stat.pickup.minecraft.iron_door":9,"stat.pickup.minecraft.cooked_fish":51,"stat.breakItem.minecraft.leather_leggings":2,"stat.craftItem.minecraft.spruce_door":9,"stat.pickup.minecraft.tripwire_hook":2,"stat.mineBlock.minecraft.magenta_glazed_terracotta":1,"stat.pickup.minecraft.bookshelf":1,"stat.mineBlock.minecraft.pumpkin":164,"stat.mineBlock.minecraft.cobblestone":17774,"stat.useItem.minecraft.beacon":5,"stat.pickup.minecraft.stone_pickaxe":56,"stat.pickup.minecraft.flint":1910,"stat.craftItem.minecraft.quartz_stairs":112,"stat.pickup.minecraft.leather_chestplate":5,"stat.mineBlock.minecraft.concrete":89,"stat.pickup.minecraft.flower_pot":4,"stat.mineBlock.minecraft.stained_glass_pane":268,"stat.pickup.minecraft.purple_glazed_terracotta":20,"stat.craftItem.minecraft.clock":1,"stat.drop.minecraft.cobblestone":2257,"stat.useItem.minecraft.chorus_flower":11,"stat.pickup.minecraft.cooked_porkchop":62,"stat.useItem.minecraft.coal_block":47,"stat.mineBlock.minecraft.dropper":4,"stat.breakItem.minecraft.iron_pickaxe":135,"stat.pickup.minecraft.iron_boots":28,"stat.pickup.minecraft.stone_hoe":18,"stat.craftItem.minecraft.furnace":111,"stat.craftItem.minecraft.lapis_block":1,"stat.useItem.minecraft.white_glazed_terracotta":2,"stat.craftItem.minecraft.iron_boots":26,"stat.mineBlock.minecraft.clay":139,"stat.mineBlock.minecraft.noteblock":139,"stat.pickup.minecraft.diamond_leggings":4,"stat.useItem.minecraft.wooden_slab":1105,"stat.drop.minecraft.spider_eye":10,"stat.craftItem.minecraft.beacon":1,"stat.useItem.minecraft.iron_door":12,"stat.craftItem.minecraft.iron_block":443,"stat.useItem.minecraft.totem_of_undying":5,"stat.craftItem.minecraft.stonebrick":4419,"stat.breakItem.minecraft.diamond_pickaxe":14,"stat.pickup.minecraft.light_blue_glazed_terracotta":9,"stat.drop.minecraft.flint_and_steel":1,"stat.drop.minecraft.wool":1,"stat.killEntity.Creeper":341,"stat.useItem.minecraft.armor_stand":1,"stat.breakItem.minecraft.iron_sword":19,"stat.pickup.minecraft.wooden_sword":11,"stat.entityKilledBy.Skeleton":51,"stat.drop.minecraft.obsidian":4,"stat.drop.minecraft.oak_stairs":4,"stat.useItem.minecraft.dropper":7,"stat.killEntity.Squid":30,"stat.sprintOneCm":114158314,"stat.mineBlock.minecraft.stone_slab":1100,"stat.useItem.minecraft.hay_block":13,"stat.useItem.minecraft.snowball":1192,"stat.entityKilledBy.VindicationIllager":1,"stat.pickup.minecraft.leather_leggings":7,"stat.craftItem.minecraft.redstone_lamp":131,"stat.drop.minecraft.cobblestone_wall":12,"stat.pickup.minecraft.sugar":11,"stat.craftItem.minecraft.leather_chestplate":5,"stat.useItem.minecraft.banner":26,"stat.entityKilledBy.Slime":1,"stat.mineBlock.minecraft.yellow_glazed_terracotta":89,"stat.craftItem.minecraft.emerald":172,"stat.pickup.minecraft.iron_block":228,"stat.killEntity.Zombie":1094,"stat.craftItem.minecraft.dye":37778,"stat.craftItem.minecraft.diamond_axe":11,"stat.mineBlock.minecraft.gold_ore":242,"stat.craftItem.minecraft.slime_ball":9,"stat.drop.minecraft.diamond_pickaxe":1,"stat.pickup.minecraft.wheat":3207,"stat.craftItem.minecraft.sandstone":219,"stat.craftItem.minecraft.purpur_pillar":3,"stat.mineBlock.minecraft.mossy_cobblestone":45,"stat.drop.minecraft.stone_stairs":66,"stat.pickup.minecraft.sign":101,"stat.craftItem.minecraft.cooked_porkchop":58,"stat.pickup.minecraft.obsidian":356,"stat.useItem.minecraft.heavy_weighted_pressure_plate":15,"stat.useItem.minecraft.iron_trapdoor":3,"stat.pickup.minecraft.coal":4935,"stat.pickup.minecraft.iron_ingot":849,"stat.useItem.minecraft.dark_oak_boat":8,"stat.craftItem.minecraft.lever":277,"stat.pickup.minecraft.gunpowder":657,"stat.pickup.minecraft.dirt":26332,"stat.useItem.minecraft.coal_ore":387,"stat.drop.minecraft.iron_shovel":1,"stat.craftItem.minecraft.sponge":1592,"stat.useItem.minecraft.dispenser":51,"stat.pickup.minecraft.command_block":1,"stat.mineBlock.minecraft.lapis_ore":132,"stat.pickup.minecraft.iron_axe":45,"stat.brewingstandInteraction":167,"stat.useItem.minecraft.stone_brick_stairs":220,"stat.mineBlock.minecraft.torch":3699,"stat.mineBlock.minecraft.red_flower":151,"stat.tradedWithVillager":205,"stat.useItem.minecraft.acacia_door":1,"stat.pickup.minecraft.magma_cream":34,"stat.pickup.minecraft.ender_eye":91,"stat.noteblockTuned":2062,"stat.craftItem.minecraft.comparator":159,"stat.craftItem.minecraft.sea_lantern":4125,"stat.craftItem.minecraft.glowstone":169,"stat.useItem.minecraft.slime":29,"stat.useItem.minecraft.birch_fence":51,"stat.mineBlock.minecraft.fence_gate":2,"stat.pickup.minecraft.rabbit_hide":3,"stat.pickup.minecraft.diamond_axe":2,"stat.pickup.minecraft.shulker_shell":2,"stat.drop.minecraft.wheat":292,"stat.pickup.minecraft.diamond_pickaxe":44,"stat.useItem.minecraft.pumpkin":603,"stat.pickup.minecraft.noteblock":141,"stat.useItem.minecraft.lava_bucket":239,"stat.drop.minecraft.netherrack":2909,"stat.pickup.minecraft.red_mushroom_block":511,"stat.useItem.minecraft.melon":53,"stat.craftItem.minecraft.wheat":9,"stat.useItem.minecraft.item_frame":67,"stat.drop.minecraft.egg":1468,"stat.useItem.minecraft.redstone_ore":60,"stat.pickup.minecraft.cooked_beef":763,"stat.useItem.minecraft.concrete":258,"stat.killEntity.Stray":1,"stat.drop.minecraft.lever":2,"stat.pickup.minecraft.dark_oak_stairs":94,"stat.mobKills":25209,"stat.pickup.minecraft.diamond_boots":15,"stat.mineBlock.minecraft.bookshelf":12,"stat.useItem.minecraft.boat":34,"stat.craftItem.minecraft.lead":14,"stat.useItem.minecraft.mossy_cobblestone":3,"stat.pickup.minecraft.diamond":104,"stat.pickup.minecraft.beetroot_seeds":59,"stat.craftItem.minecraft.spruce_stairs":48,"stat.craftItem.minecraft.map":8,"stat.breakItem.minecraft.stone_sword":30,"stat.useItem.minecraft.string":614,"stat.craftItem.minecraft.yellow_glazed_terracotta":96,"stat.useItem.minecraft.bookshelf":47,"stat.useItem.minecraft.soul_sand":35,"stat.killEntity.Blaze":388,"stat.useItem.minecraft.poisonous_potato":6,"stat.pickup.minecraft.golden_boots":1,"stat.pickup.minecraft.glowstone_dust":261,"stat.drop.minecraft.bowl":1,"stat.mineBlock.minecraft.red_mushroom":4,"stat.mineBlock.minecraft.stone_brick_stairs":58,"stat.mineBlock.minecraft.nether_brick_fence":35,"stat.drop.minecraft.poisonous_potato":16,"stat.useItem.minecraft.golden_sword":308,"stat.pickup.minecraft.splash_potion":9,"stat.craftItem.minecraft.lit_pumpkin":543,"stat.pickup.minecraft.wooden_hoe":1,"stat.craftItem.minecraft.cobblestone_wall":72,"stat.craftItem.minecraft.stone_sword":68,"stat.mineBlock.minecraft.snow_layer":1467,"stat.mineBlock.minecraft.sand":34362,"stat.craftItem.minecraft.wooden_hoe":2,"stat.craftItem.minecraft.slime":32,"stat.hopperInspected":1940,"stat.useItem.minecraft.fence_gate":8,"stat.breakItem.minecraft.flint_and_steel":7,"stat.pickup.minecraft.ghast_tear":4,"stat.trappedChestTriggered":947,"stat.drop.minecraft.rail":11,"stat.craftItem.minecraft.pumpkin_seeds":68,"stat.breakItem.minecraft.golden_chestplate":1,"stat.pickup.minecraft.wooden_button":7,"stat.mineBlock.minecraft.lapis_block":1,"stat.useItem.minecraft.minecart":188,"stat.useItem.minecraft.cooked_mutton":97,"stat.pickup.minecraft.totem_of_undying":3,"stat.drop.minecraft.diamond_helmet":2,"stat.drop.minecraft.wooden_button":1,"stat.pickup.minecraft.stone_stairs":48,"stat.craftItem.minecraft.fence_gate":6,"stat.pickup.minecraft.pumpkin_seeds":35,"stat.drop.minecraft.fireworks":738,"stat.pickup.minecraft.saddle":6,"stat.mineBlock.minecraft.soul_sand":558,"stat.pickup.minecraft.blaze_rod":510,"stat.useItem.minecraft.gray_glazed_terracotta":10,"stat.pickup.minecraft.netherrack":20926,"stat.pickup.minecraft.pumpkin":66,"stat.pickup.minecraft.spruce_door":5,"stat.useItem.minecraft.fish":79,"stat.drop.minecraft.hopper":2,"stat.useItem.minecraft.sponge":1581,"stat.pickup.minecraft.waterlily":7,"stat.mineBlock.minecraft.ice":4,"stat.craftItem.minecraft.redstone_torch":1038,"stat.useItem.minecraft.packed_ice":10,"stat.mineBlock.minecraft.gold_block":29,"stat.craftItem.minecraft.iron_hoe":2,"stat.useItem.minecraft.experience_bottle":6,"stat.drop.minecraft.stone":101,"stat.useItem.minecraft.trapped_chest":201,"stat.pickup.minecraft.melon_seeds":20,"stat.pickup.minecraft.dropper":2,"stat.pickup.minecraft.golden_leggings":15,"stat.pickup.minecraft.melon":207,"stat.dropperInspected":39,"stat.useItem.minecraft.golden_rail":747,"stat.drop.minecraft.bone":63,"stat.craftItem.minecraft.wooden_button":26,"stat.useItem.minecraft.furnace":155,"stat.pickup.minecraft.iron_leggings":35,"stat.killEntity.Llama":1,"stat.mineBlock.minecraft.snow":197,"stat.mineBlock.minecraft.gravel":12824,"stat.breakItem.minecraft.stone_axe":14,"stat.mineBlock.minecraft.beacon":3,"stat.breakItem.minecraft.diamond_axe":3,"stat.useItem.minecraft.wool":616,"stat.drop.minecraft.reeds":8,"stat.drop.minecraft.iron_axe":3,"stat.pickup.minecraft.flint_and_steel":7,"stat.useItem.minecraft.torch":8543,"stat.pickup.minecraft.golden_apple":16,"stat.pickup.minecraft.iron_nugget":4,"stat.craftItem.minecraft.redstone_block":67,"stat.craftItem.minecraft.stone_stairs":224,"stat.useItem.minecraft.log":458,"stat.pickup.minecraft.crafting_table":44,"stat.useItem.minecraft.comparator":180,"stat.craftItem.minecraft.crafting_table":85,"stat.pickup.minecraft.magenta_glazed_terracotta":2,"stat.craftItem.minecraft.boat":35,"stat.pickup.minecraft.iron_hoe":3,"stat.mineBlock.minecraft.emerald_ore":11,"stat.pickup.minecraft.redstone_block":8,"stat.useItem.minecraft.cooked_fish":54,"stat.drop.minecraft.sign":1,"stat.craftItem.minecraft.stone_button":22,"stat.drop.minecraft.planks":10,"stat.pickup.minecraft.web":72,"stat.pickup.minecraft.sapling":848,"stat.drop.minecraft.melon_seeds":3,"stat.drop.minecraft.bow":27,"stat.pickup.minecraft.beetroot":33,"stat.breakItem.minecraft.wooden_hoe":1,"stat.killEntity.WitherSkeleton":70,"stat.useItem.minecraft.wooden_pressure_plate":2,"stat.drop.minecraft.acacia_door":1,"stat.pickup.minecraft.golden_sword":42,"stat.craftItem.minecraft.sugar":67,"stat.pickup.minecraft.rabbit":1,"stat.drop.minecraft.bucket":1,"stat.useItem.minecraft.baked_potato":719,"stat.pickup.minecraft.stone_slab":516,"stat.drop.minecraft.yellow_flower":4,"stat.pickup.minecraft.yellow_flower":151,"stat.pickup.minecraft.golden_rail":508,"stat.useItem.minecraft.fishing_rod":583,"stat.drop.minecraft.wooden_axe":1,"stat.drop.minecraft.stone_pickaxe":1,"stat.craftItem.minecraft.diamond_chestplate":1,"stat.pickup.minecraft.bone":1805,"stat.useItem.minecraft.mushroom_stew":2,"stat.craftItem.minecraft.sticky_piston":105,"stat.pickup.minecraft.redstone_torch":173,"stat.horseOneCm":107871,"stat.useItem.minecraft.log2":1798,"stat.mineBlock.minecraft.slime":4,"stat.mineBlock.minecraft.brown_mushroom":15,"stat.useItem.minecraft.diamond_sword":1312,"stat.climbOneCm":2799364,"stat.useItem.minecraft.end_rod":35,"stat.craftItem.minecraft.gold_block":3,"stat.enderchestOpened":651,"stat.useItem.minecraft.redstone_torch":251,"stat.pickup.minecraft.golden_helmet":1,"stat.drop.minecraft.quartz":2,"stat.useItem.minecraft.red_flower":43,"stat.craftItem.minecraft.bone_block":2076,"stat.useItem.minecraft.leaves2":920,"stat.pickup.minecraft.anvil":1,"stat.useItem.minecraft.iron_ore":12,"stat.craftItem.minecraft.trapdoor":148,"stat.craftItem.minecraft.stone_pickaxe":222,"stat.pickup.minecraft.cobblestone":64555,"stat.useItem.minecraft.yellow_glazed_terracotta":188,"stat.craftItem.minecraft.glass_bottle":42,"stat.pickup.minecraft.soul_sand":166,"stat.useItem.minecraft.cooked_beef":284,"stat.pickup.minecraft.cactus":135,"stat.pickup.minecraft.redstone":3456,"stat.craftItem.minecraft.dispenser":30,"stat.craftItem.minecraft.book":121,"stat.mineBlock.minecraft.iron_ore":2289,"stat.pickup.minecraft.mossy_cobblestone":89,"stat.useItem.minecraft.noteblock":881,"stat.drop.minecraft.coal":41,"stat.drop.minecraft.dirt":293,"stat.useItem.minecraft.cooked_porkchop":60,"stat.pickup.minecraft.iron_shovel":39,"stat.pickup.minecraft.carpet":72,"stat.pickup.minecraft.trapdoor":10,"stat.pickup.minecraft.diamond_shovel":11,"stat.useItem.minecraft.chest_minecart":11,"stat.useItem.minecraft.sea_lantern":4646,"stat.useItem.minecraft.spruce_fence":36,"stat.craftItem.minecraft.chest_minecart":11,"stat.pickup.minecraft.paper":235,"stat.craftItem.minecraft.stick":18434,"stat.craftItem.minecraft.stained_hardened_clay":120,"stat.craftItem.minecraft.gold_nugget":13,"stat.pickup.minecraft.grass":3393,"stat.useItem.minecraft.magenta_glazed_terracotta":3,"stat.useItem.minecraft.stone_pressure_plate":4,"stat.drop.minecraft.leaves":1,"stat.pickup.minecraft.golden_horse_armor":5,"stat.pickup.minecraft.diamond_chestplate":8,"stat.entityKilledBy.Creeper":34,"stat.drop.minecraft.tipped_arrow":128,"stat.breakItem.minecraft.shears":15,"stat.mineBlock.minecraft.planks":810,"stat.drop":1202,"stat.killEntity.Sheep":126,"stat.pickup.minecraft.golden_chestplate":3,"stat.useItem.minecraft.melon_seeds":7,"stat.drop.minecraft.bread":4,"stat.useItem.minecraft.light_blue_glazed_terracotta":232,"stat.pickup.minecraft.purpur_pillar":4,"stat.craftItem.minecraft.piston":170,"stat.useItem.minecraft.quartz_stairs":182,"stat.drop.minecraft.cooked_beef":48,"stat.killEntity.Slime":928,"stat.mineBlock.minecraft.anvil":5,"stat.useItem.minecraft.blue_glazed_terracotta":54,"stat.useItem.minecraft.waterlily":2,"stat.useItem.minecraft.apple":21,"stat.mineBlock.minecraft.deadbush":1,"stat.useItem.minecraft.black_glazed_terracotta":27,"stat.drop.minecraft.chainmail_helmet":1,"stat.useItem.minecraft.porkchop":3,"stat.useItem.minecraft.carpet":4203,"stat.useItem.minecraft.potion":249,"stat.mineBlock.minecraft.purpur_pillar":4,"stat.useItem.minecraft.flower_pot":12,"stat.pickup.minecraft.fence":1129,"stat.useItem.minecraft.stone_axe":2240,"stat.craftItem.minecraft.iron_helmet":16,"stat.drop.minecraft.piston":1,"stat.craftItem.minecraft.rail":2304,"stat.drop.minecraft.bed":1,"stat.boatOneCm":4984214,"stat.drop.minecraft.magma_cream":1,"stat.craftItem.minecraft.flint_and_steel":25,"stat.useItem.minecraft.redstone_lamp":179,"stat.mineBlock.minecraft.leaves2":2286,"stat.mineBlock.minecraft.stone_stairs":39,"stat.craftItem.minecraft.iron_bars":656,"stat.mineBlock.minecraft.furnace":53,"stat.pickup.minecraft.dark_oak_fence":557,"stat.pickup.minecraft.prismarine_shard":118,"stat.drop.minecraft.stone_button":2,"stat.drop.minecraft.water_bucket":13,"stat.killEntity.CaveSpider":18,"stat.craftItem.minecraft.netherbrick":487,"stat.pickup.minecraft.oak_stairs":115,"stat.pickup.minecraft.stained_glass":841,"stat.damageDealt":970257,"stat.craftItem.minecraft.bowl":8,"stat.craftItem.minecraft.anvil":9,"stat.useItem.minecraft.crafting_table":153,"stat.useItem.minecraft.cyan_glazed_terracotta":6,"stat.pickup.minecraft.boat":9,"stat.craftItem.minecraft.stone_shovel":61,"stat.pickup.minecraft.stick":410,"stat.pickup.minecraft.spectral_arrow":16,"stat.drop.minecraft.vine":64,"stat.breakItem.minecraft.stone_pickaxe":179,"stat.drop.minecraft.iron_block":3,"stat.craftItem.minecraft.writable_book":54,"stat.useItem.minecraft.redstone_block":14,"stat.useItem.minecraft.spruce_stairs":56,"stat.craftItem.minecraft.redstone":135,"stat.pickup.minecraft.chorus_fruit":808,"stat.useItem.minecraft.cactus":207,"stat.mineBlock.minecraft.purple_glazed_terracotta":20,"stat.killEntity.Chicken":332,"stat.useItem.minecraft.iron_block":390,"stat.mineBlock.minecraft.quartz_ore":962,"stat.entityKilledBy.ElderGuardian":7,"stat.pickup.minecraft.yellow_glazed_terracotta":91,"stat.drop.minecraft.diamond_boots":1,"stat.craftItem.minecraft.fence":165,"stat.mineBlock.minecraft.leaves":4554,"stat.craftItem.minecraft.purpur_slab":6,"stat.mineBlock.minecraft.piston":6,"stat.mineBlock.minecraft.bone_block":322,"stat.mineBlock.minecraft.hay_block":3,"stat.craftItem.minecraft.tripwire_hook":138,"stat.beaconInteraction":21,"stat.pickup.minecraft.wooden_slab":65,"stat.leaveGame":918,"stat.killEntity.Parrot":36,"stat.useItem.minecraft.glowstone":40,"stat.mineBlock.minecraft.sandstone":1471,"stat.craftItem.minecraft.ender_eye":18,"stat.breakItem.minecraft.wooden_sword":2,"stat.killEntity.PigZombie":484,"stat.craftItem.minecraft.shield":6,"stat.craftItem.minecraft.stone_pressure_plate":1,"stat.drop.minecraft.feather":2906,"stat.entityKilledBy.PigZombie":15,"stat.pickup.minecraft.leaves2":879,"stat.useItem.minecraft.sandstone_stairs":9,"stat.craftItem.minecraft.noteblock":774,"stat.mineBlock.minecraft.wooden_slab":120,"stat.pickup.minecraft.leather_boots":1,"stat.killEntity.Witch":70,"stat.drop.minecraft.sand":96,"stat.drop.minecraft.gold_ingot":6,"stat.craftItem.minecraft.wooden_pickaxe":18,"stat.craftItem.minecraft.iron_door":12,"stat.useItem.minecraft.iron_shovel":16617,"stat.craftItem.minecraft.bed":35,"stat.mineBlock.minecraft.hopper":459,"stat.mineBlock.minecraft.vine":120,"stat.drop.minecraft.gravel":140,"stat.mineBlock.minecraft.rail":659,"stat.useItem.minecraft.pumpkin_seeds":54,"stat.killEntity.ZombieVillager":8,"stat.noteblockPlayed":552,"stat.drop.minecraft.red_flower":617,"stat.useItem.minecraft.double_plant":4,"stat.pickup.minecraft.prismarine":12282,"stat.pickup.minecraft.beef":467,"stat.pickup.minecraft.leather_helmet":4,"stat.useItem.minecraft.trapdoor":280,"stat.mineBlock.minecraft.stained_hardened_clay":2,"stat.useItem.minecraft.stained_glass":21851,"stat.craftItem.minecraft.prismarine":7496,"stat.useItem.minecraft.dark_oak_door":30,"stat.useItem.minecraft.ice":7,"stat.pickup.minecraft.potion":181,"stat.mineBlock.minecraft.dark_oak_fence_gate":37,"stat.useItem.minecraft.wooden_button":45,"stat.craftItem.minecraft.dropper":3,"stat.useItem.minecraft.lingering_potion":121,"stat.useItem.minecraft.dye":2756,"stat.breakItem.minecraft.diamond_boots":1,"stat.mineBlock.minecraft.stone_pressure_plate":1,"stat.useItem.minecraft.nether_brick":355,"stat.drop.minecraft.glass_bottle":12,"stat.drop.minecraft.torch":18,"stat.useItem.minecraft.jukebox":5,"stat.mineBlock.minecraft.tallgrass":4962,"stat.useItem.minecraft.splash_potion":955,"stat.useItem.minecraft.stone":8732,"stat.pickup.minecraft.arrow":4155,"stat.pickup.minecraft.wooden_pressure_plate":1,"stat.killEntity.Ghast":45,"stat.useItem.minecraft.ender_chest":13,"stat.drop.minecraft.iron_pickaxe":7,"stat.mineBlock.minecraft.chest":211,"stat.pickup.minecraft.painting":172,"stat.craftItem.minecraft.hopper":1928,"stat.pickup.minecraft.nether_brick_fence":59,"stat.useItem.minecraft.purple_glazed_terracotta":75,"stat.useItem.minecraft.reeds":89,"stat.craftItem.minecraft.nether_brick":137,"stat.craftItem.minecraft.wooden_sword":9,"stat.craftItem.minecraft.diamond_shovel":18,"stat.pickup.minecraft.wheat_seeds":7443,"stat.mineBlock.minecraft.glass":12,"stat.useItem.minecraft.enchanting_table":1,"stat.useItem.minecraft.record_13":1,"stat.mineBlock.minecraft.dirt":30729,"stat.pickup.minecraft.poisonous_potato":25,"stat.drop.minecraft.paper":1,"stat.useItem.minecraft.bread":172,"stat.pickup.minecraft.brewing_stand":1,"stat.useItem.minecraft.cobblestone":23194,"stat.useItem.minecraft.gravel":13258,"stat.mineBlock.minecraft.double_plant":115,"stat.minecartOneCm":8364867,"stat.breakItem.minecraft.golden_helmet":1,"stat.drop.minecraft.chicken":32,"stat.pickup.minecraft.iron_pickaxe":103,"stat.drop.minecraft.carrot":28,"stat.craftItem.minecraft.gold_ingot":538,"stat.pickup.minecraft.hopper":183,"stat.craftItem.minecraft.brewing_stand":7,"stat.useItem.minecraft.tallgrass":98,"stat.pickup.minecraft.apple":70,"stat.useItem.minecraft.fireworks":230,"stat.pickup.minecraft.banner":7,"stat.killEntity.ElderGuardian":3,"stat.entityKilledBy.Wolf":1,"stat.itemEnchanted":140,"stat.mineBlock.minecraft.log":2771,"stat.mineBlock.minecraft.heavy_weighted_pressure_plate":4,"stat.useItem.minecraft.wooden_door":27,"stat.useItem.minecraft.spruce_door":8,"stat.craftItem.minecraft.paper":4440,"stat.pickup.minecraft.red_flower":85,"stat.pickup.minecraft.wool":332,"stat.useItem.minecraft.chorus_fruit":6,"stat.useItem.minecraft.wooden_axe":34,"stat.craftItem.minecraft.trapped_chest":149,"stat.drop.minecraft.grass":224,"stat.pickup.minecraft.trapped_chest":2,"stat.drop.minecraft.totem_of_undying":1,"stat.drop.minecraft.pumpkin":1,"stat.mineBlock.minecraft.orange_glazed_terracotta":1,"stat.useItem.minecraft.iron_axe":7736,"stat.useItem.minecraft.orange_glazed_terracotta":23,"stat.mineBlock.minecraft.silver_glazed_terracotta":1,"stat.mineBlock.minecraft.yellow_flower":145,"stat.entityKilledBy.Witch":3,"stat.useItem.minecraft.skull":20,"stat.craftItem.minecraft.wool":2063,"stat.useItem.minecraft.snow":695,"stat.drop.minecraft.saddle":1,"stat.useItem.minecraft.concrete_powder":90,"stat.pickup.minecraft.enchanted_book":2,"stat.pickup.minecraft.glowstone":27,"stat.pickup.minecraft.writable_book":2,"stat.craftItem.minecraft.arrow":308,"stat.useItem.minecraft.obsidian":1017,"stat.pickup.minecraft.sticky_piston":6,"stat.pickup.minecraft.bow":149,"stat.craftItem.minecraft.dark_oak_door":21,"stat.craftItem.minecraft.beetroot_soup":3,"stat.useItem.minecraft.egg":4518,"stat.craftItem.minecraft.spruce_boat":1,"stat.pickup.minecraft.coal_ore":605,"stat.craftItem.minecraft.cooked_beef":317,"stat.mineBlock.minecraft.obsidian":1138,"stat.pickup.minecraft.shears":16,"stat.craftItem.minecraft.bow":47,"stat.pickup.minecraft.iron_trapdoor":1,"stat.flyOneCm":27018659,"stat.pickup.minecraft.sandstone":1316,"stat.pickup.minecraft.fish":264,"stat.craftItem.minecraft.stained_glass":22944,"stat.timeSinceDeath":62747,"stat.pickup.minecraft.quartz_ore":24,"stat.craftItem.minecraft.painting":16,"stat.cauldronFilled":2,"stat.craftItem.minecraft.purpur_block":752,"stat.killEntity.Bat":42,"stat.drop.minecraft.blaze_powder":1,"stat.useItem.minecraft.potato":1099,"stat.pickup.minecraft.nether_wart":135,"stat.pickup.minecraft.spruce_fence":87,"stat.craftItem.minecraft.concrete_powder":88,"stat.killEntity.Wolf":1,"stat.mineBlock.minecraft.coal_ore":4957,"stat.pickup.minecraft.shield":14,"stat.talkedToVillager":758,"stat.craftItem.minecraft.stone_hoe":18,"stat.drop.minecraft.baked_potato":12,"stat.mineBlock.minecraft.red_mushroom_block":253,"stat.pickup.minecraft.string":1454,"stat.craftItem.minecraft.blue_glazed_terracotta":8,"stat.mineBlock.minecraft.ladder":215,"stat.useItem.minecraft.written_book":4,"stat.mineBlock.minecraft.chorus_flower":55,"stat.useItem.minecraft.diamond_shovel":49198,"stat.breakItem.minecraft.diamond_helmet":1,"stat.craftItem.minecraft.wooden_axe":2,"stat.pickup.minecraft.bone_block":429,"stat.mineBlock.minecraft.diamond_ore":195,"stat.pickup.minecraft.fireworks":2558,"stat.pickup.minecraft.spawn_egg":2,"stat.useItem.minecraft.wooden_sword":176,"stat.breakItem.minecraft.iron_shovel":43,"stat.useItem.minecraft.ladder":1460,"stat.useItem.minecraft.diamond_ore":23,"stat.pickup.minecraft.snowball":27,"stat.killEntity.Guardian":437,"stat.diveOneCm":15405214,"stat.useItem.minecraft.sticky_piston":68,"stat.craftItem.minecraft.ladder":1374,"stat.drop.minecraft.dark_oak_fence":54,"stat.mineBlock.minecraft.stone_button":35,"stat.useItem.minecraft.chicken":1,"stat.drop.minecraft.ladder":14,"stat.pickup.minecraft.stone_axe":18,"stat.pickup.minecraft.stained_glass_pane":10,"stat.useItem.minecraft.rotten_flesh":565,"stat.drop.minecraft.apple":3,"stat.craftItem.minecraft.diamond_sword":3,"stat.drop.minecraft.sandstone":35,"stat.useItem.minecraft.sand":13297,"stat.jump":193212,"stat.mineBlock.minecraft.light_blue_glazed_terracotta":9,"stat.craftItem.minecraft.torch":4268,"stat.breakItem.minecraft.golden_leggings":2,"stat.craftItem.minecraft.fermented_spider_eye":4,"stat.mineBlock.minecraft.purpur_block":100,"stat.useItem.minecraft.glass":49,"stat.pickup.minecraft.stone_shovel":20,"stat.pickup.minecraft.gold_ore":247,"stat.useItem.minecraft.sapling":1977,"stat.mineBlock.minecraft.glass_pane":95,"stat.damageTaken":400714,"stat.mineBlock.minecraft.melon_block":84,"stat.useItem.minecraft.gold_block":72,"stat.mineBlock.minecraft.sapling":97,"stat.pickup.minecraft.log2":7053,"stat.mineBlock.minecraft.sandstone_stairs":11,"stat.entityKilledBy.ZombieVillager":10,"stat.pickup.minecraft.bed":83,"stat.drop.minecraft.nether_brick_fence":30,"stat.pickup.minecraft.concrete":89,"stat.pickup.minecraft.potato":2022,"stat.killEntity.Shulker":8,"stat.breakItem.minecraft.iron_leggings":5,"stat.entityKilledBy.Zombie":19,"stat.killEntity.Silverfish":13,"stat.useItem.minecraft.pink_glazed_terracotta":7,"stat.craftItem.minecraft.stone_slab":8244,"stat.useItem.minecraft.command_block":15,"stat.animalsBred":1531,"stat.useItem.minecraft.chest":560,"stat.craftItem.minecraft.iron_chestplate":12,"stat.pickup.minecraft.baked_potato":182,"stat.pickup.minecraft.ender_pearl":3389,"stat.drop.minecraft.wooden_slab":5,"stat.breakItem.minecraft.stone_hoe":3,"stat.pickup.minecraft.ladder":918,"stat.breakItem.minecraft.golden_boots":1,"stat.useItem.minecraft.netherrack":8648,"stat.craftItem.minecraft.stained_glass_pane":5360,"stat.mineBlock.minecraft.tnt":9,"stat.craftItem.minecraft.bookshelf":47,"stat.mineBlock.minecraft.stonebrick":1297,"stat.mineBlock.minecraft.glowstone":237,"stat.craftItem.minecraft.shears":26,"stat.craftItem.minecraft.golden_shovel":1,"stat.useItem.minecraft.cobblestone_wall":81,"stat.breakItem.minecraft.diamond_shovel":5,"stat.pickup.minecraft.iron_horse_armor":6,"stat.useItem.minecraft.writable_book":3,"stat.breakItem.minecraft.wooden_shovel":1,"stat.pickup.minecraft.torch":5199,"stat.drop.minecraft.diamond_shovel":2,"stat.pickup.minecraft.spruce_boat":10,"stat.drop.minecraft.arrow":2808,"stat.drop.minecraft.shears":1,"stat.craftItem.minecraft.compass":33,"stat.pickup.minecraft.dark_oak_fence_gate":12,"stat.craftItem.minecraft.iron_axe":35,"stat.killEntity.Ozelot":4,"stat.useItem.minecraft.lead":1,"stat.pickup.minecraft.lapis_block":2,"stat.useItem.minecraft.mutton":1,"stat.drop.minecraft.trapdoor":1,"stat.pickup.minecraft.fishing_rod":31,"stat.useItem.minecraft.planks":1778,"stat.useItem.minecraft.nether_brick_stairs":4,"stat.pickup.minecraft.porkchop":181,"stat.pickup.minecraft.glass":134,"stat.pickup.minecraft.blaze_powder":3,"stat.useItem.minecraft.water_bucket":1283,"stat.pickup.minecraft.sand":13797,"stat.craftItem.minecraft.golden_apple":15,"stat.craftItem.minecraft.dark_oak_fence":2343,"stat.entityKilledBy.Spider":6,"stat.pickup.minecraft.name_tag":5,"stat.useItem.minecraft.record_cat":2,"stat.drop.minecraft.splash_potion":1,"stat.pickup.minecraft.activator_rail":2,"stat.aviateOneCm":97665582,"stat.useItem.minecraft.ender_pearl":1415,"stat.useItem.minecraft.brown_mushroom":1,"stat.craftItem.minecraft.cooked_fish":53,"stat.craftItem.minecraft.blaze_powder":72,"stat.useItem.minecraft.spawn_egg":524,"stat.useItem.minecraft.red_glazed_terracotta":15,"stat.craftItem.minecraft.hardened_clay":104,"stat.useItem.minecraft.oak_stairs":51,"stat.mineBlock.minecraft.dark_oak_stairs":87,"stat.useItem.minecraft.dark_oak_stairs":316,"stat.drop.minecraft.dark_oak_fence_gate":2,"stat.drop.minecraft.stone_slab":19,"stat.pickup.minecraft.fence_gate":2,"stat.pickup.minecraft.filled_map":7,"stat.pickup.minecraft.furnace":36,"stat.useItem.minecraft.redstone":1395,"stat.mineBlock.minecraft.redstone_lamp":55,"stat.pickup.minecraft.iron_chestplate":29,"stat.useItem.minecraft.stone_stairs":134,"stat.pickup.minecraft.skull":5,"stat.pickup.minecraft.acacia_door":1,"stat.useItem.minecraft.hopper":2416,"stat.craftItem.minecraft.heavy_weighted_pressure_plate":4,"stat.mineBlock.minecraft.oak_stairs":106,"stat.playOneMinute":40050836,"stat.drop.minecraft.string":81,"stat.useItem.minecraft.shears":3643,"stat.mineBlock.minecraft.brown_mushroom_block":1,"stat.pickup.minecraft.iron_bars":191,"stat.pickup.minecraft.dispenser":10,"stat.mineBlock.minecraft.dark_oak_fence":431,"stat.craftItem.minecraft.carpet":3672,"stat.mineBlock.minecraft.netherrack":43085,"stat.mineBlock.minecraft.dispenser":23,"stat.craftItem.minecraft.dark_oak_stairs":248,"stat.drop.minecraft.flint":28,"stat.craftItem.minecraft.golden_rail":366,"stat.useItem.minecraft.quartz_ore":9,"stat.craftItem.minecraft.iron_nugget":4,"stat.breakItem.minecraft.leather_helmet":2,"stat.pickup.minecraft.cooked_chicken":2478,"stat.fallOneCm":5221929,"stat.drop.minecraft.dye":460,"stat.craftItem.minecraft.chest":2455,"stat.craftItem.minecraft.banner":19,"stat.useItem.minecraft.nether_brick_fence":1,"stat.mineBlock.minecraft.lever":78,"stat.pickup.minecraft.red_mushroom":22,"stat.useItem.minecraft.iron_hoe":73,"stat.pickup.minecraft.comparator":16,"stat.pickup.minecraft.feather":1311,"stat.pickup.minecraft.record_cat":3,"stat.mineBlock.minecraft.spruce_fence":35,"stat.craftItem.minecraft.dark_oak_fence_gate":2075,"stat.pickup.minecraft.lead":10,"stat.useItem.minecraft.stone_pickaxe":25531,"stat.craftItem.minecraft.iron_leggings":12,"stat.useItem.minecraft.stone_sword":5274,"stat.killEntity.Rabbit":1,"stat.pickup.minecraft.redstone_ore":228,"stat.craftItem.minecraft.oak_stairs":20,"stat.entityKilledBy.Ghast":3,"stat.pickup.minecraft.chainmail_boots":3,"stat.craftItem.minecraft.golden_pickaxe":1,"stat.drop.minecraft.stick":7,"stat.useItem.minecraft.iron_bars":625,"stat.mineBlock.minecraft.monster_egg":7,"stat.mineBlock.minecraft.quartz_stairs":68,"stat.useItem.minecraft.bone_block":1919,"stat.drop.minecraft.black_glazed_terracotta":1,"stat.killEntity.LavaSlime":98,"stat.pickup.minecraft.log":1439,"stat.useItem.minecraft.brown_glazed_terracotta":11,"stat.mineBlock.minecraft.golden_rail":360,"stat.breakItem.minecraft.iron_boots":8,"stat.craftItem.minecraft.hopper_minecart":2,"stat.pickup.minecraft.tallgrass":119,"stat.breakItem.minecraft.iron_helmet":8,"stat.pickup.minecraft.wooden_door":70,"stat.entityKilledBy.Enderman":10,"stat.mineBlock.minecraft.iron_block":339,"stat.breakItem.minecraft.iron_chestplate":4,"stat.useItem.minecraft.beetroot_soup":3,"stat.killEntity.PolarBear":2,"stat.craftItem.minecraft.snow":718,"stat.pickup.minecraft.diamond_helmet":10,"stat.craftItem.minecraft.cooked_chicken":254,"stat.useItem.minecraft.stone_hoe":1169,"stat.craftItem.minecraft.flower_pot":6,"stat.craftItem.minecraft.golden_boots":1,"stat.useItem.minecraft.beetroot_seeds":68,"stat.sneakTime":882670,"stat.mineBlock.minecraft.cobblestone_wall":16,"stat.entityKilledBy.Blaze":7,"stat.useItem.minecraft.brewing_stand":8,"stat.mineBlock.minecraft.jukebox":1,"stat.useItem.minecraft.beetroot":1,"stat.pickup.minecraft.chest":95,"stat.craftItem.minecraft.enchanting_table":1,"stat.craftItem.minecraft.leather_leggings":4,"stat.useItem.minecraft.lapis_block":1,"stat.pickup.minecraft.stone_pressure_plate":1,"stat.pickup.minecraft.lit_pumpkin":165,"stat.drop.minecraft.beetroot":9,"stat.useItem.minecraft.repeater":468,"stat.drop.minecraft.leather_helmet":1,"stat.craftItem.minecraft.stone_brick_stairs":264,"stat.useItem.minecraft.silver_glazed_terracotta":17,"stat.craftItem.minecraft.iron_trapdoor":2,"stat.swimOneCm":8504332,"stat.mineBlock.minecraft.spruce_stairs":9,"stat.useItem.minecraft.dirt":18539,"stat.pickup.minecraft.purpur_block":99,"stat.craftItem.minecraft.melon_block":3,"stat.drop.minecraft.ender_pearl":28,"stat.useItem.minecraft.golden_pickaxe":1,"stat.mineBlock.minecraft.magma":276,"stat.pickup.minecraft.quartz_stairs":4,"stat.mineBlock.minecraft.carpet":807,"stat.pickup.minecraft.gold_block":31,"stat.drop.minecraft.fence":2,"stat.mineBlock.minecraft.redstone_block":9,"stat.useItem.minecraft.stone_shovel":7685,"stat.pickup.minecraft.glass_bottle":119,"stat.killEntity.ZombieHorse":2,"stat.useItem.minecraft.red_mushroom":7,"stat.drop.minecraft.wheat_seeds":3392,"stat.craftItem.minecraft.wooden_slab":996,"stat.useItem.minecraft.sign":511,"stat.drop.minecraft.log":62,"stat.pickup.minecraft.mutton":227,"stat.drop.minecraft.activator_rail":5,"stat.useItem.minecraft.lever":210,"stat.pickup.minecraft.wooden_axe":3,"stat.mineBlock.minecraft.coal_block":1,"stat.breakItem.minecraft.golden_sword":11,"stat.pickup.minecraft.dark_oak_door":21,"stat.pickup.minecraft.stonebrick":149,"stat.mineBlock.minecraft.nether_brick":259,"stat.useItem.minecraft.purpur_pillar":4,"stat.drop.minecraft.log2":38,"stat.drop.minecraft.anvil":1,"stat.drop.minecraft.potion":2,"stat.useItem.minecraft.stone_slab":7996,"stat.useItem.minecraft.bed":136,"stat.craftItem.minecraft.stone":3650,"stat.craftItem.minecraft.armor_stand":1,"stat.mineBlock.minecraft.crafting_table":79,"stat.useItem.minecraft.diamond_pickaxe":180520,"stat.mineBlock.minecraft.quartz_block":2,"stat.killEntity.Endermite":16,"stat.useItem.minecraft.carrot":674,"stat.useItem.minecraft.ender_eye":72,"stat.useItem.minecraft.wooden_shovel":60,"stat.drop.minecraft.golden_apple":3,"stat.useItem.minecraft.bucket":1691,"stat.pickup.minecraft.stone_button":40,"stat.pickup.minecraft.slime_ball":654,"stat.useItem.minecraft.purpur_block":677,"stat.drop.minecraft.blaze_rod":2,"stat.craftItem.minecraft.diamond_pickaxe":57,"stat.craftItem.minecraft.clay":104,"stat.craftItem.minecraft.jukebox":4,"stat.pickup.minecraft.gravel":15357,"stat.useItem.minecraft.glass_bottle":127,"stat.useItem.minecraft.diamond_axe":12109,"stat.entityKilledBy.Guardian":42,"stat.useItem.minecraft.stained_glass_pane":5098,"stat.pickup.minecraft.stone_brick_stairs":404,"stat.pickup.minecraft.diamond_sword":17,"stat.pickup.minecraft.brick":1,"stat.useItem.minecraft.bedrock":680,"stat.killEntity.SkeletonHorse":3,"stat.useItem.minecraft.wooden_hoe":63,"stat.pickup.minecraft.iron_helmet":35,"stat.useItem.minecraft.piston":54,"stat.craftItem.minecraft.bread":146,"stat.entityKilledBy.CaveSpider":5,"stat.pickup.minecraft.spider_eye":103,"stat.useItem.minecraft.stone_button":61,"stat.pickup.minecraft.diamond_ore":23,"stat.useItem.minecraft.cooked_chicken":4481,"stat.pickup.minecraft.iron_ore":1827,"stat.mineBlock.minecraft.iron_bars":17,"stat.pickup.minecraft.leaves":1646,"stat.pickup.minecraft.leather":267,"stat.dispenserInspected":205,"stat.useItem.minecraft.wooden_pickaxe":746,"stat.pickup.minecraft.reeds":1762,"stat.pickup.minecraft.prismarine_crystals":318,"stat.useItem.minecraft.end_portal_frame":1,"stat.drop.minecraft.cooked_chicken":223,"stat.craftItem.minecraft.glass":3413,"stat.craftItem.minecraft.cauldron":2,"stat.sleepInBed":282,"stat.craftItem.minecraft.baked_potato":796,"stat.drop.minecraft.shulker_shell":1,"stat.killEntity.Cow":244,"stat.pickup.minecraft.minecart":137,"stat.killEntity.Pig":69,"stat.craftItem.minecraft.iron_sword":44,"stat.pickup.minecraft.piston":54,"stat.breakItem.minecraft.fishing_rod":3,"stat.walkOneCm":213761355,"stat.playerKills":3,"stat.pickup.minecraft.clay_ball":512,"stat.mineBlock.minecraft.trapped_chest":51,"stat.useItem.minecraft.dark_oak_fence_gate":2274,"stat.useItem.minecraft.spruce_boat":4,"stat.pickup.minecraft.stone":47963,"stat.mineBlock.minecraft.wool":90,"stat.pickup.minecraft.silver_glazed_terracotta":2,"stat.drop.minecraft.diamond_leggings":2,"stat.craftItem.minecraft.hay_block":11,"stat.useItem.minecraft.leaves":2013,"stat.craftItem.minecraft.minecart":13,"stat.pickup.minecraft.gold_ingot":90,"stat.useItem.minecraft.prismarine":17184,"stat.killEntity.Skeleton":913,"stat.mineBlock.minecraft.cactus":213,"stat.pickup.minecraft.netherbrick":3,"stat.mineBlock.minecraft.redstone_torch":127,"stat.killEntity.Spider":400,"stat.pickup.minecraft.bread":17,"stat.craftItem.minecraft.spruce_fence":45,"stat.pickup.minecraft.quartz":523,"stat.pickup.minecraft.blue_glazed_terracotta":28,"stat.breakItem.minecraft.iron_axe":14,"stat.pickup.minecraft.water_bucket":28,"stat.drop.minecraft.prismarine":71,"stat.useItem.minecraft.hopper_minecart":2,"stat.mineBlock.minecraft.redstone_ore":870,"stat.pickup.minecraft.elytra":148,"stat.pickup.minecraft.lava_bucket":2,"stat.craftItem.minecraft.coal_block":8,"stat.craftItem.minecraft.brick":25,"stat.mineBlock.minecraft.stone":163347,"stat.breakItem.minecraft.wooden_pickaxe":9,"stat.useItem.minecraft.sandstone":539}