{"stat.damageDealt":7370,"achievement.exploreAllBiomes":{"value":0,"progress":["Forest","Extreme Hills","The End","Savanna","Savanna Plateau","Hell","Sky","ForestHills"]},"stat.craftItem.minecraft.minecart":1,"achievement.openInventory":7,"stat.climbOneCm":356,"stat.fallOneCm":1593,"stat.flyOneCm":103288,"stat.damageTaken":810,"stat.timeSinceDeath":942,"stat.killEntity.Enderman":734,"stat.playOneMinute":27809,"stat.leaveGame":4,"stat.deaths":1,"stat.walkOneCm":402967,"stat.jump":111,"stat.swimOneCm":17,"stat.mobKills":734,"stat.sprintOneCm":11708}